emojito/__init__.py
emojito-0.1.0.post2.dist-info/METADATA
emojito-0.1.0.post2.dist-info/WHEEL
emojito-0.1.0.post2.dist-info/RECORD
