Metadata-Version: 2.1
Name: emojito
Version: 0.1.0.post2
Summary: Define your own shortnames to be replaced with emojis or other content.
Home-page: https://gitlab.com/emojito/emojito
License: GPL-3.0-or-later
Author: Maximillian Strand
Author-email: maxi@millian.se
Requires-Python: >=3.10,<4.0
Classifier: License :: OSI Approved :: GNU General Public License v3 or later (GPLv3+)
Classifier: Programming Language :: Python :: 3
Classifier: Programming Language :: Python :: 3.10
Classifier: Programming Language :: Python :: 3.11
Requires-Dist: beautifulsoup4 (>=4.11.1,<5.0.0)
Project-URL: Repository, https://gitlab.com/emojito/emojito
